{
    "name": "KSRobot_IR",
    "version": "0.4.0",
    "description": "Extension for KAISE KSRobot IR receiver module",
    "license": "MIT",
    "dependencies": {
        "core": "*"
    },
    "files": [
        "KSRobot.ts",
        "enums.d.ts",
        "KSRobot_IR.cpp",
        "ReceiverIR.cpp",
        "ReceiverIR.h",
        "RemoteIR.h",
        "TransmitterIR.cpp",
        "TransmitterIR.h",
        "README.md",
        "_locales/zh/KSRobotIR-strings.json" 
    ],
    "public": true
}
